task1/lsfr.sv
module lsfr (
    input logic         clk, //clock
    input logic         rst, //reset
    input logic         en,
    output logic [7:1]  data_out //pseudo random output
);
    logic [7:1]         sreg;

always_ff @ (posedge clk, posedge rst)
    if(rst)
        sreg <= 7'b1;
    else
        if(en)
            sreg <= {sreg[7:1], sreg[7] ^ sreg[3]};

assign data_out = sreg;
endmodule

task1/lsfr.vcd
$version Generated by VerilatedVcd $end
$timescale 1ps $end

 $scope module TOP $end
  $var wire  1 # clk $end
  $var wire  7 & data_out [7:1] $end
  $var wire  1 % en $end
  $var wire  1 $ rst $end
  $scope module lsfr $end
   $var wire  1 # clk $end
   $var wire  7 & data_out [7:1] $end
   $var wire  1 % en $end
   $var wire  1 $ rst $end
   $var wire  7 ' sreg [7:1] $end
  $upscope $end
 $upscope $end
$enddefinitions $end


#0
1#
1$
0%
b0000000 &
b0000000 '
#1
0#
#2
1#
0$
b0000001 &
b0000001 '
#3
0#
#4
1#
#5
0#
#6
1#
#7
0#
#8
1#
#9
0#
#10
1#
#11
0#
#12
1#
#13
0#
#14
1#
#15
0#
#16
1#
#17
0#
#18
1#
#19
0#
#20
1#
#21
0#
#22
1#
#23
0#
#24
1#
#25
0#
#26
1#
#27
0#
#28
1#
#29
0#
#30
1#
#31
0#
#32
1#
#33
0#
#34
1#
#35
0#
#36
1#
#37
0#
#38
1#
#39
0#
#40
1#
#41
0#
#42
1#
#43
0#
#44
1#
#45
0#
#46
1#
#47
0#
#48
1#
#49
0#
#50
1#
#51
0#
#52
1#
#53
0#
#54
1#
#55
0#
#56
1#
#57
0#
#58
1#
#59
0#
#60
1#
#61
0#
#62
1#
#63
0#
#64
1#
#65
0#
#66
1#
1%
#67
0#
#68
1#
0%
b0000010 &
b0000010 '
#69
0#
#70
1#
#71
0#
#72
1#
#73
0#
#74
1#
#75
0#
#76
1#
#77
0#
#78
1#
#79
0#
#80
1#
#81
0#
#82
1#
#83
0#
#84
1#
#85
0#
#86
1#
#87
0#
#88
1#
#89
0#
#90
1#
#91
0#
#92
1#
#93
0#
#94
1#
#95
0#
#96
1#
#97
0#
#98
1#
1%
#99
0#
#100
1#
0%
b0000100 &
b0000100 '
#101
0#
#102
1#
#103
0#
#104
1#
#105
0#
#106
1#
#107
0#
#108
1#
#109
0#
#110
1#
#111
0#
#112
1#
#113
0#
#114
1#
#115
0#
#116
1#
#117
0#
#118
1#
#119
0#
#120
1#
#121
0#
#122
1#
1%
#123
0#
#124
1#
0%
b0001001 &
b0001001 '
#125
0#
#126
1#
#127
0#
#128
1#
#129
0#
#130
1#
#131
0#
#132
1#
#133
0#
#134
1#
#135
0#
#136
1#
#137
0#
#138
1#
#139
0#
#140
1#
#141
0#
#142
1#
#143
0#
#144
1#
#145
0#
#146
1#
1%
#147
0#
#148
1#
0%
b0010010 &
b0010010 '
#149
0#
#150
1#
#151
0#
#152
1#
#153
0#
#154
1#
#155
0#
#156
1#
1%
#157
0#
#158
1#
0%
b0100100 &
b0100100 '
#159
0#
#160
1#
#161
0#
#162
1#
#163
0#
#164
1#
#165
0#
#166
1#
1%
#167
0#
#168
1#
0%
b1001001 &
b1001001 '
#169
0#
#170
1#
#171
0#
#172
1#
1%
#173
0#
#174
1#
0%
b0010011 &
b0010011 '
#175
0#
#176
1#
#177
0#
#178
1#
#179
0#
#180
1#
1%
#181
0#
#182
1#
0%
b0100110 &
b0100110 '
#183
0#
#184
1#
#185
0#
#186
1#
#187
0#
#188
1#
1%
#189
0#
#190
1#
0%
b1001101 &
b1001101 '
#191
0#
#192
1#
#193
0#
#194
1#
#195
0#
#196
1#
1%
#197
0#
#198
1#
0%
b0011010 &
b0011010 '
#199
0#
#200
1#
#201
0#
#202
1#
#203
0#
#204
1#
#205
0#
#206
1#
#207
0#
#208
1#
#209
0#
#210
1#
#211
0#
#212
1#
#213
0#
#214
1#
#215
0#
#216
1#
#217
0#
#218
1#
#219
0#
#220
1#
#221
0#
#222
1#
#223
0#
#224
1#
#225
0#
#226
1#
#227
0#
#228
1#
1%
#229
0#
#230
1#
0%
b0110100 &
b0110100 '
#231
0#
#232
1#
#233
0#
#234
1#
#235
0#
#236
1#
#237
0#
#238
1#
1%
#239
0#
#240
1#
0%
b1101001 &
b1101001 '
#241
0#
#242
1#
#243
0#
#244
1#
#245
0#
#246
1#
1%
#247
0#
#248
1#
0%
b1010011 &
b1010011 '
#249
0#
#250
1#
#251
0#
#252
1#
#253
0#
#254
1#
1%
#255
0#
#256
1#
0%
b0100111 &
b0100111 '
#257
0#
#258
1#
#259
0#
#260
1#
#261
0#
#262
1#
#263
0#
#264
1#
1%
#265
0#
#266
1#
0%
b1001111 &
b1001111 '
#267
0#
#268
1#
#269
0#
#270
1#
1%
#271
0#
#272
1#
0%
b0011110 &
b0011110 '
#273
0#
#274
1#
#275
0#
#276
1#
#277
0#
#278
1#
#279
0#
#280
1#
1%
#281
0#
#282
1#
0%
b0111101 &
b0111101 '
#283
0#
#284
1#
#285
0#
#286
1#
#287
0#
#288
1#
#289
0#
#290
1#
#291
0#
#292
1#
1%
#293
0#
#294
1#
0%
b1111011 &
b1111011 '
#295
0#
#296
1#
#297
0#
#298
1#
#299
0#
#300
1#
#301
0#
#302
1#
1%
#303
0#
#304
1#
0%
b1110111 &
b1110111 '
#305
0#
#306
1#
#307
0#
#308
1#
#309
0#
#310
1#
#311
0#
#312
1#
#313
0#
#314
1#
#315
0#
#316
1#
#317
0#
#318
1#
#319
0#
#320
1#
1%
#321
0#
#322
1#
0%
b1101110 &
b1101110 '
#323
0#
#324
1#
#325
0#
#326
1#
#327
0#
#328
1#
1%
#329
0#
#330
1#
0%
b1011100 &
b1011100 '
#331
0#
#332
1#
#333
0#
#334
1#
#335
0#
#336
1#
#337
0#
#338
1#
1%
#339
0#
#340
1#
0%
b0111000 &
b0111000 '
#341
0#
#342
1#
#343
0#
#344
1#
#345
0#
#346
1#
#347
0#
#348
1#
1%
#349
0#
#350
1#
0%
b1110000 &
b1110000 '
#351
0#
#352
1#
#353
0#
#354
1#
#355
0#
#356
1#
1%
#357
0#
#358
1#
0%
b1100001 &
b1100001 '
#359
0#
#360
1#
#361
0#
#362
1#
#363
0#
#364
1#
#365
0#
#366
1#
1%
#367
0#
#368
1#
0%
b1000011 &
b1000011 '
#369
0#
#370
1#
#371
0#
#372
1#
#373
0#
#374
1#
#375
0#
#376
1#
1%
#377
0#
#378
1#
0%
b0000111 &
b0000111 '
#379
0#
#380
1#
#381
0#
#382
1#
#383
0#
#384
1#
1%
#385
0#
#386
1#
0%
b0001111 &
b0001111 '
#387
0#
#388
1#
#389
0#
#390
1#
#391
0#
#392
1#
#393
0#
#394
1#
1%
#395
0#
#396
1#
0%
b0011111 &
b0011111 '
#397
0#
#398
1#
#399
0#
#400
1#
#401
0#
#402
1#
#403
0#
#404
1#
1%
#405
0#
#406
1#
0%
b0111111 &
b0111111 '
#407
0#
#408
1#
#409
0#
#410
1#
#411
0#
#412
1#
#413
0#
#414
1#
1%
#415
0#
#416
1#
0%
b1111111 &
b1111111 '
#417
0#
#418
1#
#419
0#
#420
1#
#421
0#
#422
1#
#423
0#
#424
1#
1%
#425
0#
#426
1#
0%
b1111110 &
b1111110 '
#427
0#
#428
1#
#429
0#
#430
1#
#431
0#
#432
1#
#433
0#
#434
1#
1%
#435
0#
#436
1#
0%
b1111100 &
b1111100 '
#437
0#
#438
1#
#439
0#
#440
1#
#441
0#
#442
1#
#443
0#
#444
1#
#445
0#
#446
1#
#447
0#
#448
1#
#449
0#
#450
1#
#451
0#
#452
1#
#453
0#
#454
1#
#455
0#
#456
1#
#457
0#
#458
1#
#459
0#
#460
1#
#461
0#
#462
1#
#463
0#
#464
1#
#465
0#
#466
1#
#467
0#
#468
1#
#469
0#
#470
1#
1%
#471
0#
#472
1#
0%
b1111000 &
b1111000 '
#473
0#
#474
1#
#475
0#
#476
1#
#477
0#
#478
1#
#479
0#
#480
1#
1%
#481
0#
#482
1#
0%
b1110001 &
b1110001 '
#483
0#
#484
1#
#485
0#
#486
1#
#487
0#
#488
1#
#489
0#
#490
1#
#491
0#
#492
1#
1%
#493
0#
#494
1#
b1100011 &
b1100011 '
#495
0#
#496
1#
0%
b1000111 &
b1000111 '
#497
0#
#498
1#
#499
0#
#500
1#
#501
0#
#502
1#
#503
0#
#504
1#
#505
0#
#506
1#
1%
#507
0#
#508
1#
0%
b0001110 &
b0001110 '
#509
0#
#510
1#
#511
0#
#512
1#
#513
0#
#514
1#
#515
0#
#516
1#
#517
0#
#518
1#
#519
0#
#520
1#
#521
0#
#522
1#
#523
0#
#524
1#
#525
0#
#526
1#
#527
0#
#528
1#
#529
0#
#530
1#
#531
0#
#532
1#
#533
0#
#534
1#
#535
0#
#536
1#
#537
0#
#538
1#
1%
#539
0#
#540
1#
0%
b0011101 &
b0011101 '
#541
0#
#542
1#
#543
0#
#544
1#
#545
0#
#546
1#
#547
0#
#548
1#
#549
0#
#550
1#
#551
0#
#552
1#
#553
0#
#554
1#
#555
0#
#556
1#
#557
0#
#558
1#
#559
0#
#560
1#
#561
0#
#562
1#
1%
#563
0#
#564
1#
0%
b0111011 &
b0111011 '
#565
0#
#566
1#
#567
0#
#568
1#
#569
0#
#570
1#
#571
0#
#572
1#
#573
0#
#574
1#
#575
0#
#576
1#
#577
0#
#578
1#
#579
0#
#580
1#
1%
#581
0#
#582
1#
0%
b1110110 &
b1110110 '
#583
0#
#584
1#
#585
0#
#586
1#
#587
0#
#588
1#
#589
0#
#590
1#
#591
0#
#592
1#
#593
0#
#594
1#
#595
0#
#596
1#
#597
0#
#598
1#
#599
0#
#600
1#
1%
#601
0#
#602
1#
0%
b1101100 &
b1101100 '
#603
0#
#604
1#
#605
0#
#606
1#
#607
0#
#608
1#
#609
0#
#610
1#
#611
0#
#612
1#
#613
0#
#614
1#
#615
0#
#616
1#
#617
0#
#618
1#
#619
0#
#620
1#
#621
0#
#622
1#
#623
0#
#624
1#
#625
0#
#626
1#
#627
0#
#628
1#
#629
0#
#630
1#
1%
#631
0#
#632
1#
0%
b1011000 &
b1011000 '
#633
0#
#634
1#
#635
0#
#636
1#
#637
0#
#638
1#
#639
0#
#640
1#
#641
0#
#642
1#
#643
0#
#644
1#
#645
0#
#646
1#
#647
0#
#648
1#
#649
0#
#650
1#
#651
0#
#652
1#
#653
0#
#654
1#
#655
0#
#656
1#
#657
0#
#658
1#
#659
0#
#660
1#
#661
0#
#662
1#
#663
0#
#664
1#
#665
0#
#666
1#
1%
#667
0#
#668
1#
0%
b0110001 &
b0110001 '
#669
0#
#670
1#
#671
0#
#672
1#
#673
0#
#674
1#
#675
0#
#676
1#
#677
0#
#678
1#
#679
0#
#680
1#
#681
0#
#682
1#
#683
0#
#684
1#
#685
0#
#686
1#
#687
0#
#688
1#
#689
0#
#690
1#
1%
#691
0#
#692
1#
0%
b1100010 &
b1100010 '
#693
0#
#694
1#
#695
0#
#696
1#
#697
0#
#698
1#
#699
0#
#700
1#
#701
0#
#702
1#
#703
0#
#704
1#
#705
0#
#706
1#
#707
0#
#708
1#
#709
0#
#710
1#
#711
0#
#712
1#
#713
0#
#714
1#
#715
0#
#716
1#
#717
0#
#718
1#
#719
0#
#720
1#
#721
0#
#722
1#
#723
0#
#724
1#
#725
0#
#726
1#
#727
0#
#728
1#
#729
0#
#730
1#
1%
#731
0#
#732
1#
0%
b1000101 &
b1000101 '
#733
0#
#734
1#
#735
0#
#736
1#
#737
0#
#738
1#
#739
0#
#740
1#
#741
0#
#742
1#
#743
0#
#744
1#
#745
0#
#746
1#
#747
0#
#748
1#
#749
0#
#750
1#
#751
0#
#752
1#
#753
0#
#754
1#
1%
#755
0#
#756
1#
0%
b0001010 &
b0001010 '
#757
0#
#758
1#
#759
0#
#760
1#
#761
0#
#762
1#
#763
0#
#764
1#
#765
0#
#766
1#
#767
0#
#768
1#
#769
0#
#770
1#
#771
0#
#772
1#
#773
0#
#774
1#
#775
0#
#776
1#
#777
0#
#778
1#
#779
0#
#780
1#
#781
0#
#782
1#
#783
0#
#784
1#
1%
#785
0#
#786
1#
0%
b0010100 &
b0010100 '
#787
0#
#788
1#
#789
0#
#790
1#
#791
0#
#792
1#
#793
0#
#794
1#
#795
0#
#796
1#
#797
0#
#798
1#
#799
0#
#800
1#
#801
0#
#802
1#
#803
0#
#804
1#
#805
0#
#806
1#
1%
#807
0#
#808
1#
0%
b0101001 &
b0101001 '
#809
0#
#810
1#
#811
0#
#812
1#
#813
0#
#814
1#
#815
0#
#816
1#
#817
0#
#818
1#
#819
0#
#820
1#
#821
0#
#822
1#
#823
0#
#824
1#
#825
0#
#826
1#
#827
0#
#828
1#
#829
0#
#830
1#
1%
#831
0#
#832
1#
0%
b1010010 &
b1010010 '
#833
0#
#834
1#
#835
0#
#836
1#
#837
0#
#838
1#
#839
0#
#840
1#
#841
0#
#842
1#
#843
0#
#844
1#
#845
0#
#846
1#
#847
0#
#848
1#
#849
0#
#850
1#
#851
0#
#852
1#
#853
0#
#854
1#
#855
0#
#856
1#
#857
0#
#858
1#
#859
0#
#860
1#
1%
#861
0#
#862
1#
0%
b0100101 &
b0100101 '
#863
0#
#864
1#
#865
0#
#866
1#
#867
0#
#868
1#
#869
0#
#870
1#
#871
0#
#872
1#
#873
0#
#874
1#
#875
0#
#876
1#
#877
0#
#878
1#
#879
0#
#880
1#
#881
0#
#882
1#
#883
0#
#884
1#
#885
0#
#886
1#
1%
#887
0#
#888
1#
0%
b1001011 &
b1001011 '
#889
0#
#890
1#
#891
0#
#892
1#
#893
0#
#894
1#
#895
0#
#896
1#
#897
0#
#898
1#
#899
0#
#900
1#
#901
0#
#902
1#
#903
0#
#904
1#
#905
0#
#906
1#
#907
0#
#908
1#
#909
0#
#910
1#
#911
0#
#912
1#
#913
0#
#914
1#
1%
#915
0#
#916
1#
0%
b0010111 &
b0010111 '
#917
0#
#918
1#
#919
0#
#920
1#
#921
0#
#922
1#
#923
0#
#924
1#
#925
0#
#926
1#
#927
0#
#928
1#
#929
0#
#930
1#
#931
0#
#932
1#
#933
0#
#934
1#
#935
0#
#936
1#
#937
0#
#938
1#
#939
0#
#940
1#
1%
#941
0#
#942
1#
0%
b0101111 &
b0101111 '
#943
0#
#944
1#
#945
0#
#946
1#
#947
0#
#948
1#
#949
0#
#950
1#
#951
0#
#952
1#
#953
0#
#954
1#
#955
0#
#956
1#
#957
0#
#958
1#
#959
0#
#960
1#
#961
0#
#962
1#
#963
0#
#964
1#
#965
0#
#966
1#
1%
#967
0#
#968
1#
0%
b1011111 &
b1011111 '
#969
0#
#970
1#
#971
0#
#972
1#
#973
0#
#974
1#
#975
0#
#976
1#
#977
0#
#978
1#
#979
0#
#980
1#
#981
0#
#982
1#
#983
0#
#984
1#
#985
0#
#986
1#
#987
0#
#988
1#
#989
0#
#990
1#
#991
0#
#992
1#
1%
#993
0#
#994
1#
0%
b0111110 &
b0111110 '
#995
0#
#996
1#
#997
0#
#998
1#
#999
0#
#1000
1#
#1001
0#
#1002
1#
#1003
0#
#1004
1#
#1005
0#
#1006
1#
#1007
0#
#1008
1#
#1009
0#
#1010
1#
#1011
0#
#1012
1#
#1013
0#
#1014
1#
#1015
0#
#1016
1#
#1017
0#
#1018
1#
#1019
0#
#1020
1#
#1021
0#
#1022
1#
#1023
0#
#1024
1#
#1025
0#
#1026
1#
#1027
0#
#1028
1#
1%
#1029
0#
#1030
1#
0%
b1111101 &
b1111101 '
#1031
0#
#1032
1#
#1033
0#
#1034
1#
#1035
0#
#1036
1#
#1037
0#
#1038
1#
#1039
0#
#1040
1#
#1041
0#
#1042
1#
#1043
0#
#1044
1#
#1045
0#
#1046
1#
#1047
0#
#1048
1#
#1049
0#
#1050
1#
#1051
0#
#1052
1#
#1053
0#
#1054
1#
#1055
0#
#1056
1#
#1057
0#
#1058
1#
#1059
0#
#1060
1#
#1061
0#
#1062
1#
#1063
0#
#1064
1#
#1065
0#
#1066
1#
1%
#1067
0#
#1068
1#
0%
b1111010 &
b1111010 '
#1069
0#
#1070
1#
#1071
0#
#1072
1#
#1073
0#
#1074
1#
#1075
0#
#1076
1#
#1077
0#
#1078
1#
#1079
0#
#1080
1#
#1081
0#
#1082
1#
#1083
0#
#1084
1#
#1085
0#
#1086
1#
#1087
0#
#1088
1#
#1089
0#
#1090
1#
#1091
0#
#1092
1#
#1093
0#
#1094
1#
1%
#1095
0#
#1096
1#
0%
b1110101 &
b1110101 '
#1097
0#
#1098
1#
#1099
0#
#1100
1#
#1101
0#
#1102
1#
#1103
0#
#1104
1#
#1105
0#
#1106
1#
#1107
0#
#1108
1#
#1109
0#
#1110
1#
#1111
0#
#1112
1#
#1113
0#
#1114
1#
#1115
0#
#1116
1#
#1117
0#
#1118
1#
#1119
0#
#1120
1#
#1121
0#
#1122
1#
#1123
0#
#1124
1#
#1125
0#
#1126
1#
#1127
0#
#1128
1#
#1129
0#
#1130
1#
#1131
0#
#1132
1#
#1133
0#
#1134
1#
1%
#1135
0#
#1136
1#
0%
b1101010 &
b1101010 '
#1137
0#
#1138
1#
#1139
0#
#1140
1#
#1141
0#
#1142
1#
#1143
0#
#1144
1#
#1145
0#
#1146
1#
#1147
0#
#1148
1#
#1149
0#
#1150
1#
#1151
0#
#1152
1#
#1153
0#
#1154
1#
#1155
0#
#1156
1#
#1157
0#
#1158
1#
#1159
0#
#1160
1#
#1161
0#
#1162
1#
#1163
0#
#1164
1#
#1165
0#
#1166
1#
1%
#1167
0#
#1168
1#
0%
b1010101 &
b1010101 '
#1169
0#
#1170
1#
#1171
0#
#1172
1#
#1173
0#
#1174
1#
#1175
0#
#1176
1#
#1177
0#
#1178
1#
#1179
0#
#1180
1#
#1181
0#
#1182
1#
#1183
0#
#1184
1#
#1185
0#
#1186
1#
#1187
0#
#1188
1#
#1189
0#
#1190
1#
#1191
0#
#1192
1#
#1193
0#
#1194
1#
#1195
0#
#1196
1#
#1197
0#
#1198
1#
#1199
0#
#1200
1#
1%
#1201
0#
#1202
1#
0%
b0101010 &
b0101010 '
#1203
0#
#1204
1#
#1205
0#
#1206
1#
#1207
0#
#1208
1#
#1209
0#
#1210
1#
#1211
0#
#1212
1#
#1213
0#
#1214
1#
#1215
0#
#1216
1#
#1217
0#
#1218
1#
#1219
0#
#1220
1#
#1221
0#
#1222
1#
#1223
0#
#1224
1#
#1225
0#
#1226
1#
#1227
0#
#1228
1#
#1229
0#
#1230
1#
#1231
0#
#1232
1#
#1233
0#
#1234
1#
1%
#1235
0#
#1236
1#
0%
b1010100 &
b1010100 '
